{
    "id": 95,
    "text": " ููุฃูู ูุฏููุฉ ูุฑุฏ ุจุนูู ููุจูโค ูุง ุชุฐุจู ุฃุจุฏุง ูุงูู ุญูุงุฉ ุชุชูุฑุฏ ุจู ๐ฟ .. #ุนุทูุฑู๐ #ุดูุดู๐",
    "sentiment": "ุฅูุฌุงุจู",
    "probability": "51.9",
    "word_sentiment": {
        "ููุงูู": {
            "score": -0.052
        },
        "ูุฏููู": {
            "score": 0.047
        },
        "ูุฑุฏ": {
            "score": -0.081
        },
        "ุจุนูู": {
            "score": 0.174
        },
        "ููุจู": {
            "score": 0.113
        },
        "ูุง": {
            "score": -0.056
        },
        "ุชุฐุจู": {
            "score": -0.067
        },
        "ุงุจุฏุง": {
            "score": -0.01
        },
        "ูุงูู": {
            "score": -0.052
        },
        "ุญูุงู": {
            "score": 0.143
        },
        "ุชุชูุฑุฏ": {
            "score": -0.081
        },
        "ุจู": {
            "score": 0
        }
    }
}