{
    "id": 198,
    "text": " صبااح الياسمين على الناس الرايقين 💛 #صباح_الخير",
    "sentiment": "إيجابي",
    "probability": "57.4",
    "word_sentiment": {
        "صبااح": {
            "score": 0.097
        },
        "الياسمين": {
            "score": -0.024
        },
        "علا": {
            "score": 0.021
        },
        "الناس": {
            "score": 0.127
        },
        "الرايقين": {
            "score": 0.076
        }
    }
}