{
    "id": 78,
    "text": " : ูุจุฑูู ุฒูุฌุชู ุญุงูู ูู ุชูุงุฆู ุงูุฒูุฌ :- ูุนูู ุงูุง ุฑุงุญ ุงุตูุฑ ุฃุจ ๐ญุ ุงูุฏูุชูุฑ :- ูุง ุญุถุฑุชู ุฑุงุญ ุชุตูุฑ ุณูู ุงุจ ๐ ูู ๐๐๐",
    "sentiment": "ุฅูุฌุงุจู",
    "probability": "77.7",
    "word_sentiment": {
        "ูุจุฑูู": {
            "score": 0.212
        },
        "ุฒูุฌุชู": {
            "score": 0.385
        },
        "ุญุงูู": {
            "score": 0.078
        },
        "ูู": {
            "score": -0.017
        },
        "ุชูุงุกู": {
            "score": 0.26
        },
        "ุงูุฒูุฌ": {
            "score": -0.121
        },
        "ูุนูู": {
            "score": 0.086
        },
        "ุงูุง": {
            "score": 0.083
        },
        "ุฑุงุญ": {
            "score": 0.54
        },
        "ุงุตูุฑ": {
            "score": -0.005
        },
        "ุงุจ": {
            "score": -0.084
        },
        "ุงูุฏูุชูุฑ": {
            "score": 0.335
        },
        "ูุง": {
            "score": -0.056
        },
        "ุญุถุฑุชู": {
            "score": -0.085
        },
        "ุชุตูุฑ": {
            "score": -0.022
        },
        "ุณูู": {
            "score": -0.33
        },
        "ูู": {
            "score": -0.011
        }
    }
}