{
    "id": 279,
    "text": "\tثلاث مرات بيادون بالكوتشيلا وأحس 😭",
    "sentiment": "سلبي",
    "probability": "62.7",
    "word_sentiment": {
        "ثلاث": {
            "score": -0.406
        },
        "مرات": {
            "score": -0.041
        },
        "بيادون": {
            "score": 0.047
        },
        "بالكوتشيلا": {
            "score": -0.115
        },
        "واحس": {
            "score": -0.005
        }
    }
}