{
    "id": 986,
    "text": "\tانا: هذا الترم صاير اجتماعي اختبر: ميت ضحك 😭",
    "sentiment": "سلبي",
    "probability": "61.3",
    "word_sentiment": {
        "انا": {
            "score": 0.083
        },
        "هذا": {
            "score": -0.04
        },
        "الترم": {
            "score": 0.042
        },
        "صاير": {
            "score": -0.005
        },
        "اجتماعي": {
            "score": 0.226
        },
        "اختبر": {
            "score": -0.859
        },
        "ميت": {
            "score": 0.007
        },
        "ضحك": {
            "score": 0.085
        }
    }
}