{
    "id": 901,
    "text": "\tتحبه او تكرهه هذا شي راجع لك .. لكن من شبه المستحيل انك تحصل لاعب يعطيك مباراة كامله بعمر ال او 😓 ماشاء الل…",
    "sentiment": "إيجابي",
    "probability": "50.9",
    "word_sentiment": {
        "تحبه": {
            "score": 0.103
        },
        "او": {
            "score": -0.06
        },
        "تكرهه": {
            "score": 0.056
        },
        "هذا": {
            "score": -0.04
        },
        "شي": {
            "score": -0.055
        },
        "راجع": {
            "score": -0.116
        },
        "لك": {
            "score": -0.097
        },
        "لكن": {
            "score": -0.137
        },
        "من": {
            "score": 0.07
        },
        "شبه": {
            "score": -0.017
        },
        "المستحيل": {
            "score": 0.171
        },
        "انك": {
            "score": 0.137
        },
        "تحصل": {
            "score": -0.033
        },
        "لاعب": {
            "score": 0.137
        },
        "يعطيك": {
            "score": 0.194
        },
        "مباراه": {
            "score": -0.238
        },
        "كامله": {
            "score": 0.033
        },
        "بعمر": {
            "score": -0.025
        },
        "ال": {
            "score": 0
        },
        "ماشاء": {
            "score": -0.002
        },
        "الل": {
            "score": -0.045
        }
    }
}