{
    "id": 648,
    "text": " ุฌุฑุนุฉ ุฃูู ุ ูู ูููู ุชุนุงูู: ๏ดฟูุง ุชุฏุฑู ูุนู ุงููู ูุญุฏุซ ุจุนุฏ ุฐูู ุฃูุฑุง๏ดพ ๐ธ",
    "sentiment": "ุณูุจู",
    "probability": "50.8",
    "word_sentiment": {
        "ุฌุฑุนู": {
            "score": 0.045
        },
        "ุงูู": {
            "score": -0.081
        },
        "ูู": {
            "score": -0.017
        },
        "ูููู": {
            "score": 0.005
        },
        "ุชุนุงูุง": {
            "score": 0.128
        },
        "ูุง": {
            "score": -0.056
        },
        "ุชุฏุฑู": {
            "score": -0.042
        },
        "ูุนู": {
            "score": 0.021
        },
        "ุงููู": {
            "score": -0.045
        },
        "ูุญุฏุซ": {
            "score": 0.075
        },
        "ุจุนุฏ": {
            "score": -0.065
        },
        "ุฐูู": {
            "score": -0.025
        },
        "ุงูุฑุง": {
            "score": 0.025
        }
    }
}