{
    "id": 331,
    "text": "\tุงูู ุจุฑุฌ ุงูุนุฑุจ .. ุชูููุช ุนูู ุงููู ๐",
    "sentiment": "ุฅูุฌุงุจู",
    "probability": "50.9",
    "word_sentiment": {
        "ุงูุง": {
            "score": -0.056
        },
        "ุจุฑุฌ": {
            "score": -0.054
        },
        "ุงูุนุฑุจ": {
            "score": 0.137
        },
        "ุชูููุช": {
            "score": 0.034
        },
        "ุนูุง": {
            "score": 0.021
        },
        "ุงููู": {
            "score": -0.045
        }
    }
}