{
    "id": 249,
    "text": " كيف دمرت أحلام ليفربول؟ 🎙️ جوزيه مورينيو: \"قبل مباراتنا ضدهم في أنفيلد شعرت انهم بهذا اليوم يجهزون للإحتفال بال…",
    "sentiment": "إيجابي",
    "probability": "66.6",
    "word_sentiment": {
        "كيف": {
            "score": 0.072
        },
        "دمرت": {
            "score": -0.031
        },
        "احلام": {
            "score": 0.078
        },
        "ليفربول": {
            "score": 0.006
        },
        "جوزيه": {
            "score": 0.009
        },
        "مورينيو": {
            "score": 0.049
        },
        "قبل": {
            "score": 0.113
        },
        "مباراتنا": {
            "score": 0.122
        },
        "ضدهم": {
            "score": 0.129
        },
        "في": {
            "score": -0.017
        },
        "انفيلد": {
            "score": 0.036
        },
        "شعرت": {
            "score": 0.197
        },
        "انهم": {
            "score": -0.119
        },
        "بهذا": {
            "score": -0.118
        },
        "اليوم": {
            "score": 0.004
        },
        "يجهزون": {
            "score": -0.021
        },
        "للاحتفال": {
            "score": 0.286
        },
        "بال": {
            "score": -0.103
        }
    }
}